CHANGELOG.md
LICENSE
MANIFEST.in
README.md
setup.py
bin_scripts/ticketus-admin
bin_scripts/ticketus_mailgw_imap4
import_scripts/ticketus_import_freshdesk
import_scripts/ticketus_import_github
ticketus/__init__.py
ticketus/local_settings.py.example
ticketus/settings.py
ticketus/urls.py
ticketus/wsgi.py
ticketus.egg-info/PKG-INFO
ticketus.egg-info/SOURCES.txt
ticketus.egg-info/dependency_links.txt
ticketus.egg-info/not-zip-safe
ticketus.egg-info/requires.txt
ticketus.egg-info/top_level.txt
ticketus/accounts/__init__.py
ticketus/accounts/templates/registration/login.html
ticketus/core/__init__.py
ticketus/core/admin.py
ticketus/core/forms.py
ticketus/core/models.py
ticketus/core/utils.py
ticketus/core/management/__init__.py
ticketus/core/management/commands/__init__.py
ticketus/core/management/commands/init.py
ticketus/core/migrations/0001_initial.py
ticketus/core/migrations/0002_auto_20141223_1827.py
ticketus/core/migrations/0003_auto_20141227_1258.py
ticketus/core/migrations/0004_auto_20141227_1312.py
ticketus/core/migrations/0005_auto_20141227_1729.py
ticketus/core/migrations/0006_auto_20141227_1735.py
ticketus/core/migrations/0007_auto_20141228_0646.py
ticketus/core/migrations/0008_auto_20141228_0651.py
ticketus/core/migrations/0009_auto_20150115_1118.py
ticketus/core/migrations/__init__.py
ticketus/mailgw/__init__.py
ticketus/mailgw/backend_imap4.py
ticketus/mailgw/utils.py
ticketus/tags/__init__.py
ticketus/tags/admin.py
ticketus/tags/models.py
ticketus/tags/urls.py
ticketus/tags/views.py
ticketus/tags/migrations/0001_initial.py
ticketus/tags/migrations/0002_auto_20150104_1020.py
ticketus/tags/migrations/__init__.py
ticketus/tags/static/js/top_tags_selector.js
ticketus/tags/templates/includes/ticket_tags.html
ticketus/tags/templates/includes/top_tags_selector.html
ticketus/ui/__init__.py
ticketus/ui/urls.py
ticketus/ui/utils.py
ticketus/ui/views.py
ticketus/ui/static/css/base.css
ticketus/ui/static/css/ticket.css
ticketus/ui/static/js/comment_preview.js
ticketus/ui/static/js/markdown.min.js
ticketus/ui/templates/base.html
ticketus/ui/templates/includes/connecter_border.html
ticketus/ui/templates/includes/navbar.html
